failcore/__init__.py
failcore/adapters/__init__.py
failcore/adapters/base.py
failcore/adapters/langchain/__init__.py
failcore/adapters/langchain/detector.py
failcore/adapters/langchain/mapper.py
failcore/adapters/langchain/wrapper.py
failcore/adapters/mcp/__init__.py
failcore/adapters/mcp/codec.py
failcore/adapters/mcp/egress_integration.py
failcore/adapters/mcp/security.py
failcore/adapters/mcp/session.py
failcore/adapters/mcp/transport.py
failcore/adapters/proxy/__init__.py
failcore/adapters/proxy/transport.py
failcore/adapters/sdk/__init__.py
failcore/api/__init__.py
failcore/api/context.py
failcore/api/guard.py
failcore/api/presets.py
failcore/api/result.py
failcore/api/run.py
failcore/api/session.py
failcore/cli/__init__.py
failcore/cli/main.py
failcore/cli/commands/__init__.py
failcore/cli/commands/analyze_cmd.py
failcore/cli/commands/audit_cmd.py
failcore/cli/commands/list_cmd.py
failcore/cli/commands/proxy_cmd.py
failcore/cli/commands/replay_cmd.py
failcore/cli/commands/report_cmd.py
failcore/cli/commands/run_cmd.py
failcore/cli/commands/service_cmd.py
failcore/cli/commands/show_cmd.py
failcore/cli/commands/trace_cmd.py
failcore/cli/commands/ui_cmd.py
failcore/cli/commands/validate_cmd.py
failcore/cli/renderers/__init__.py
failcore/cli/renderers/json.py
failcore/cli/renderers/text.py
failcore/cli/renderers/html/__init__.py
failcore/cli/renderers/html/layout.py
failcore/cli/renderers/html/primitives.py
failcore/cli/renderers/html/styles.py
failcore/cli/renderers/html/utils.py
failcore/cli/renderers/html/sections/__init__.py
failcore/cli/renderers/html/sections/audit_report.py
failcore/cli/renderers/html/sections/common.py
failcore/cli/renderers/html/sections/trace_report.py
failcore/cli/views/__init__.py
failcore/cli/views/audit_report.py
failcore/cli/views/replay_diff.py
failcore/cli/views/replay_run.py
failcore/cli/views/trace_report.py
failcore/cli/views/trace_show.py
failcore/cli/views/trace_viewer.py
failcore/core/__init__.py
failcore-0.1.3.dist-info/METADATA
failcore-0.1.3.dist-info/WHEEL
failcore-0.1.3.dist-info/entry_points.txt
failcore-0.1.3.dist-info/licenses/LICENSE
failcore-0.1.3.dist-info/RECORD
