Metadata-Version: 2.4
Name: failcore
Version: 0.1.3
Summary: A minimal execution runtime and tracing toolkit for agent plans.
Author: ZiLing(FailCore)
License:                                  Apache License
License-File: LICENSE
Keywords: agent,audit,debugging,execution,runtime,tracing
Classifier: Development Status :: 4 - Beta
Classifier: Intended Audience :: Developers
Classifier: License :: OSI Approved :: Apache Software License
Classifier: Programming Language :: Python :: 3
Classifier: Programming Language :: Python :: 3 :: Only
Classifier: Programming Language :: Python :: 3.10
Classifier: Programming Language :: Python :: 3.11
Classifier: Programming Language :: Python :: 3.12
Classifier: Programming Language :: Python :: 3.13
Classifier: Topic :: Software Development :: Debuggers
Classifier: Topic :: Software Development :: Libraries
Requires-Python: >=3.10
Provides-Extra: dev
Requires-Dist: build>=1.2.2; extra == 'dev'
Requires-Dist: pytest>=9.0.2; extra == 'dev'
Requires-Dist: ruff>=0.6.0; extra == 'dev'
Requires-Dist: twine>=5.1.1; extra == 'dev'
Provides-Extra: langchain
Requires-Dist: langchain-core<2.0.0,>=0.3.0; extra == 'langchain'
Provides-Extra: mcp
Requires-Dist: mcp>=1.2.0; extra == 'mcp'
Provides-Extra: otel
Requires-Dist: opentelemetry-api>=1.20.0; extra == 'otel'
Requires-Dist: opentelemetry-exporter-otlp-proto-http>=1.20.0; extra == 'otel'
Requires-Dist: opentelemetry-sdk>=1.20.0; extra == 'otel'
Provides-Extra: proxy
Requires-Dist: fastapi>=0.110; extra == 'proxy'
Requires-Dist: uvicorn>=0.23; extra == 'proxy'
Provides-Extra: server
Requires-Dist: fastapi>=0.110; extra == 'server'
Requires-Dist: uvicorn>=0.23; extra == 'server'
Provides-Extra: ui
Requires-Dist: fastapi>=0.110; extra == 'ui'
Requires-Dist: jinja2>=3.1; extra == 'ui'
Requires-Dist: uvicorn>=0.23; extra == 'ui'
